LPLG/__init__.py
LPLG/parse.py
LPLG/setup.py
LPLG/config/__init__.py
LPLG/config/config.py
LPLG/schemas/__init__.py
LPLG/schemas/schemas.py
LPLGather-0.0.1.dist-info/METADATA
LPLGather-0.0.1.dist-info/WHEEL
LPLGather-0.0.1.dist-info/top_level.txt
LPLGather-0.0.1.dist-info/RECORD
